./.coveragerc
./.editorconfig
./.gitattributes
./.gitignore
./.pre-commit-config.yaml
./CHANGELOG.md
./CLAUDE.md
./CONTRIBUTING.md
./LICENSE
./Makefile
./PERFORMANCE_OPTIMIZATIONS.md
./PKG-INFO
./README.md
./ROADMAP.md
./TROUBLESHOOTING.md
./benchmark_performance.py
./ccusage_monitor.py
./pyproject.toml
./pyrightconfig.json
./pytest.ini
./requirements-dev.txt
./requirements.txt
./.github/workflows/README.md
./.github/workflows/publish-release.yml
./.github/workflows/publish-test.yml
./.github/workflows/test.yml
./ccusage_monitor/__init__.py
./ccusage_monitor/__main__.py
./ccusage_monitor/main.py
./ccusage_monitor/protocols.py
./ccusage_monitor/py.typed
./ccusage_monitor/app/__init__.py
./ccusage_monitor/app/main.py
./ccusage_monitor/app/main_rich.py
./ccusage_monitor/core/__init__.py
./ccusage_monitor/core/cache.py
./ccusage_monitor/core/calculations.py
./ccusage_monitor/core/config.py
./ccusage_monitor/core/data.py
./ccusage_monitor/ui/__init__.py
./ccusage_monitor/ui/display.py
./ccusage_monitor/ui/rich_display.py
./docs/CONFIG.md
./docs/INSTALL.md
./docs/RICH_UI.md
./docs/USAGE.md
./docs/sc.png
./scripts/check_package_hash.py
./scripts/check_pypi_version.py
./tests/__init__.py
./tests/test_app_main.py
./tests/test_core_cache.py
./tests/test_core_calculations.py
./tests/test_core_config.py
./tests/test_core_data.py
./tests/test_ui_display.py
ccusage_monitor-1.0.1.dist-info/METADATA
ccusage_monitor-1.0.1.dist-info/WHEEL
ccusage_monitor-1.0.1.dist-info/entry_points.txt
ccusage_monitor-1.0.1.dist-info/licenses/LICENSE
ccusage_monitor-1.0.1.dist-info/RECORD
