Metadata-Version: 2.4
Name: ccusage-monitor
Version: 1.0.1
Summary: Real-time Claude token usage monitor with beautiful terminal interface
Project-URL: Homepage, https://github.com/zhiyue/ccusage-monitor
Project-URL: Repository, https://github.com/zhiyue/ccusage-monitor
Project-URL: Issues, https://github.com/zhiyue/ccusage-monitor/issues
Author-email: zhiyue <cszhiyue@gmail.com>
License: MIT
License-File: LICENSE
Classifier: Development Status :: 4 - Beta
Classifier: Environment :: Console
Classifier: Intended Audience :: Developers
Classifier: License :: OSI Approved :: MIT License
Classifier: Operating System :: OS Independent
Classifier: Programming Language :: Python :: 3
Classifier: Programming Language :: Python :: 3.8
Classifier: Programming Language :: Python :: 3.9
Classifier: Programming Language :: Python :: 3.10
Classifier: Programming Language :: Python :: 3.11
Classifier: Programming Language :: Python :: 3.12
Classifier: Topic :: Utilities
Requires-Python: >=3.8
Requires-Dist: pytz>=2021.1
Requires-Dist: rich>=13.0.0
